keygen_py-0.1.8.dist-info/METADATA
keygen_py-0.1.8.dist-info/WHEEL
keygen_py-0.1.8.dist-info/licenses/LICENSE
keygen_sh.libs/libgcc_s-e52197c3.so.1
keygen_sh/errors.py
keygen_sh/certificate.pyi
keygen_sh/_errors.pyi
keygen_sh/license.pyi
keygen_sh/machine.pyi
keygen_sh/__init__.py
keygen_sh/machine_file.pyi
keygen_sh/entitlement.pyi
keygen_sh/config.pyi
keygen_sh/component.pyi
keygen_sh/license_file.pyi
keygen_sh/__init__.pyi
keygen_sh/keygen_sh.pypy39-pp73-aarch64-linux-gnu.so
keygen_py-0.1.8.dist-info/RECORD
