Metadata-Version: 2.4
Name: keygen-py
Version: 0.1.8
License-File: LICENSE
Summary: Unofficial Keygen SDK for Python. Integrate license activation and offline licensing. Wrapper around keygen-rs rust crate
Author-email: Terra Quantum AG <info@terraquantum.swiss>, Cedric Kring <ck@terraquantum.swiss>, Steven Beckers <sb@terraquantum.swiss>
License: MIT
Requires-Python: >=3.9
